cacheia_schemas/__init__.py
cacheia_schemas/exceptions.py
cacheia_schemas/interfaces.py
cacheia_schemas/values.py
cacheia_schemas-1.0.0.post3.dist-info/METADATA
cacheia_schemas-1.0.0.post3.dist-info/WHEEL
cacheia_schemas-1.0.0.post3.dist-info/top_level.txt
cacheia_schemas-1.0.0.post3.dist-info/RECORD
