Metadata-Version: 2.1
Name: cacheia_schemas
Version: 1.0.0.post3
Summary: Schemas for cacheia library
Author-email: TeiaLabs <contato@teialabs.com>
Keywords: cache,schemas,lib
Requires-Python: >=3.12
Requires-Dist: pydantic <3,>=2
Requires-Dist: pydantic-settings <3,>=2
